{
  "2": {
    "0": [
      "rw",
      "fh",
      "gd",
      "fd",
      "nq"
    ],
    "1": [
      "dz",
      "fs",
      "yc",
      "bk",
      "sz",
      "mg",
      "hl",
      "vy",
      "rg",
      "ez",
      "mb",
    ],
    "2": [
      "ku",
      "nk",
      "ky"
    ],
    "3": [
      "ph",
      "tz",
      "xo",
      "ly",
      "gy",
      "um"
    ]
  },
  "3": {
    "1": [
      "yli",
      "ojo",
      "ehl",
      "uhl",
      "ugg",
      "ymp",
      "nne",
      "dii",
      "eka",
      "ogl",
      "ghu",
      "qib",
      "mei",
      "azl",
      "uig"
    ],
    "2": [
      "yic",
      "ths",
      "eee",
      "nse",
      "ity",
      "ork",
      "aws",
      "eal",
      "nah",
      "smr",
      "ahn",
      "msa",
      "oic",
      "cch",
      "avy",
      "aic",
      "ian"
    ],
    "3": [
      "ary",
      "tzi",
      "ely",
      "ogy",
      "aku",
      "ism"
    ],
    "4": [
      "tze",
      "gly"
    ]
  },
  "4": {
    "1": [
      "okan",
      "naka",
      "arah",
      "aruh",
      "tely",
      "prez",
      "lons",
      "iten",
      "krit",
      "caxi",
      "alka",
      "coti",
      "fize",
      "amur"
    ],
    "2": [
      "roid",
      "galy",
      "amsa",
      "tral",
      "opic",
      "hina",
      "tcha",
      "tiah",
      "mekh",
      "ower",
      "oick",
      "aidi",
      "raph"
    ],
    "3": [
      "ness",
      "taph"
    ],
    "4": [
      "aphy"
    ]
  }
}











